mediallm/__init__.py
mediallm/api.py
mediallm/main.py
mediallm/analysis/__init__.py
mediallm/analysis/ffprobe_analyzer.py
mediallm/analysis/prompt_enhancer.py
mediallm/analysis/workspace_scanner.py
mediallm/constants/__init__.py
mediallm/constants/media_formats.py
mediallm/constants/prompts.py
mediallm/core/__init__.py
mediallm/core/action_inference.py
mediallm/core/command_builder.py
mediallm/core/file_type_detector.py
mediallm/core/filter_validator.py
mediallm/core/json_repair.py
mediallm/core/llm.py
mediallm/core/output_generator.py
mediallm/core/query_parser.py
mediallm/core/task_router.py
mediallm/interface/__init__.py
mediallm/interface/command_handler.py
mediallm/interface/command_handlers.py
mediallm/interface/confirm_dialog.py
mediallm/interface/core_app.py
mediallm/interface/display_utils.py
mediallm/interface/file_utils.py
mediallm/interface/interactive_prompt.py
mediallm/interface/prompt_ui.py
mediallm/interface/spinner.py
mediallm/interface/system_utils.py
mediallm/interface/terminal_interface.py
mediallm/processing/__init__.py
mediallm/processing/command_executor.py
mediallm/processing/media_file_handler.py
mediallm/safety/__init__.py
mediallm/safety/access_control.py
mediallm/safety/data_protection.py
mediallm/utils/__init__.py
mediallm/utils/config.py
mediallm/utils/data_models.py
mediallm/utils/exceptions.py
mediallm/utils/format_utils.py
mediallm/utils/media_validator.py
mediallm/utils/model_manager.py
mediallm/utils/path_utils.py
mediallm/utils/table_factory.py
mediallm/utils/version.py
mediallm/utils/logging/__init__.py
mediallm/utils/logging/config.py
mediallm/utils/logging/context.py
mediallm-0.0.3.dist-info/METADATA
mediallm-0.0.3.dist-info/WHEEL
mediallm-0.0.3.dist-info/entry_points.txt
mediallm-0.0.3.dist-info/RECORD
