Metadata-Version: 2.4
Name: mediallm
Version: 0.0.3
Summary: Natural language to FFmpeg, instantly and privately
Project-URL: Homepage, https://github.com/iamarunbrahma/mediallm
Project-URL: Repository, https://github.com/iamarunbrahma/mediallm.git
Project-URL: Bug Tracker, https://github.com/iamarunbrahma/mediallm/issues
Project-URL: Documentation, https://github.com/iamarunbrahma/mediallm/blob/main/README.md
Project-URL: Changelog, https://github.com/iamarunbrahma/mediallm/releases
Author-email: Arun Brahma <mithubrahma94@gmail.com>
Maintainer-email: Arun Brahma <mithubrahma94@gmail.com>
Keywords: ai,audio,automation,cli,conversion,ffmpeg,llm,local-ai,media-processing,natural-language,ollama,privacy,video
Classifier: Development Status :: 4 - Beta
Classifier: Environment :: Console
Classifier: Intended Audience :: Developers
Classifier: Intended Audience :: End Users/Desktop
Classifier: License :: OSI Approved :: MIT License
Classifier: Operating System :: OS Independent
Classifier: Programming Language :: Python :: 3
Classifier: Programming Language :: Python :: 3.10
Classifier: Programming Language :: Python :: 3.11
Classifier: Programming Language :: Python :: 3.12
Classifier: Programming Language :: Python :: 3.13
Classifier: Topic :: Multimedia :: Sound/Audio :: Conversion
Classifier: Topic :: Multimedia :: Video :: Conversion
Classifier: Topic :: Software Development :: Libraries :: Python Modules
Classifier: Topic :: System :: Shells
Classifier: Topic :: Utilities
Requires-Python: >=3.10
Requires-Dist: ollama==0.5.3
Requires-Dist: prompt-toolkit==3.0.48
Requires-Dist: pydantic==2.11.0
Requires-Dist: python-dotenv==1.0.1
Requires-Dist: rich==14.1.0
Requires-Dist: typer==0.16.1
Provides-Extra: docs
Requires-Dist: mkdocs-material==9.5.44; extra == 'docs'
Requires-Dist: mkdocs-mermaid2-plugin==1.1.1; extra == 'docs'
Requires-Dist: mkdocs==1.6.1; extra == 'docs'
Requires-Dist: mkdocstrings[python]==0.26.1; extra == 'docs'
Requires-Dist: pymdown-extensions==10.11.2; extra == 'docs'
